{
  "users": {
    "harsh": {
      "created": 1746360425108,
      "lastLogin": 1746512565057,
      "loginCount": 57,
      "password": "1212",
      "preferences": {}
    },
    "sneha": {
      "created": 1746360520638,
      "lastLogin": 1746390660947,
      "loginCount": 15,
      "password": "1212",
      "preferences": {}
    },
    "test": {
      "created": 1746360559421,
      "lastLogin": 1746512092882,
      "loginCount": 66,
      "password": "1212",
      "preferences": {}
    },
    "haharsh": {
      "created": 1746368271872,
      "lastLogin": 1746368271872,
      "loginCount": 1,
      "password": "1212",
      "preferences": {}
    },
    "user": {
      "created": 1746369087478,
      "lastLogin": 1746369403457,
      "loginCount": 6,
      "password": "12",
      "preferences": {}
    },
    "dinesh": {
      "created": 1746507626144,
      "lastLogin": 1746508714894,
      "loginCount": 6,
      "password": "1234",
      "preferences": {}
    },
    "HARSH": {
      "created": 1746507948643,
      "lastLogin": 1746507948643,
      "loginCount": 1,
      "password": "1212",
      "preferences": {}
    }
  }
}